{"ASN-163-PROA": {"PC": 0, "PE": 0, "PG": 0, "PI": 0, "PS": 0, "PA": 0, "CL": 0, "SM": 0, "CHOL": 0}, "ALA-165-PROA": {"PC": 0, "PE": 0, "PG": 0, "PI": 0, "PS": 0, "PA": 0, "CL": 0, "SM": 0, "CHOL": 0}, "LEU-166-PROA": {"PC": 0, "PE": 0, "PG": 0, "PI": 0, "PS": 0, "PA": 0, "CL": 0, "SM": 0, "CHOL": 0}, "TYR-281-PROA": {"PC": 0, "PE": 0, "PG": 0, "PI": 0, "PS": 0, "PA": 0, "CL": 0, "SM": 0, "CHOL": 0}, "GLY-282-PROA": {"PC": 0, "PE": 0, "PG": 0, "PI": 0, "PS": 0, "PA": 0, "CL": 0, "SM": 0, "CHOL": 0}, "TRP-283-PROA": {"PC": 0, "PE": 0, "PG": 0, "PI": 0, "PS": 0, "PA": 0, "CL": 0, "SM": 0, "CHOL": 0}, "LEU-284-PROA": {"PC": 0, "PE": 0, "PG": 0, "PI": 0, "PS": 0, "PA": 0, "CL": 0, "SM": 0, "CHOL": 0}, "TRP-285-PROA": {"PC": 0, "PE": 0, "PG": 0, "PI": 0, "PS": 0, "PA": 0, "CL": 0, "SM": 0, "CHOL": 0}, "PHE-286-PROA": {"PC": 0, "PE": 0, "PG": 0, "PI": 0, "PS": 0, "PA": 0, "CL": 0, "SM": 0, "CHOL": 0}, "ILE-287-PROA": {"PC": 0, "PE": 0, "PG": 0, "PI": 0, "PS": 0, "PA": 0, "CL": 0, "SM": 0, "CHOL": 0}, "SER-288-PROA": {"PC": 0, "PE": 0, "PG": 0, "PI": 0, "PS": 0, "PA": 0, "CL": 0, "SM": 0, "CHOL": 0}, "GLN-289-PROA": {"PC": 0, "PE": 0, "PG": 0, "PI": 0, "PS": 0, "PA": 0, "CL": 0, "SM": 0, "CHOL": 0}, "PRO-290-PROA": {"PC": 0, "PE": 0, "PG": 0, "PI": 0, "PS": 0, "PA": 0, "CL": 0, "SM": 0, "CHOL": 0}, "LEU-291-PROA": {"PC": 0, "PE": 0, "PG": 0, "PI": 0, "PS": 0, "PA": 0, "CL": 0, "SM": 0, "CHOL": 0}, "PHE-292-PROA": {"PC": 0, "PE": 0, "PG": 0, "PI": 0, "PS": 0, "PA": 0, "CL": 0, "SM": 0, "CHOL": 0}, "LYS-293-PROA": {"PC": 0, "PE": 0, "PG": 0, "PI": 0, "PS": 0, "PA": 0, "CL": 0, "SM": 0, "CHOL": 0}, "LEU-294-PROA": {"PC": 0, "PE": 0, "PG": 0, "PI": 0, "PS": 0, "PA": 0, "CL": 0, "SM": 0, "CHOL": 0}, "LEU-295-PROA": {"PC": 0, "PE": 0, "PG": 0, "PI": 0, "PS": 0, "PA": 0, "CL": 0, "SM": 0, "CHOL": 0}, "LYS-296-PROA": {"PC": 0, "PE": 0, "PG": 0, "PI": 0, "PS": 0, "PA": 0, "CL": 0, "SM": 0, "CHOL": 0}, "TRP-297-PROA": {"PC": 0, "PE": 0, "PG": 0, "PI": 0, "PS": 0, "PA": 0, "CL": 0, "SM": 0, "CHOL": 0}, "ILE-298-PROA": {"PC": 0, "PE": 0, "PG": 0, "PI": 0, "PS": 0, "PA": 0, "CL": 0, "SM": 0, "CHOL": 0}, "HSD-299-PROA": {"PC": 0, "PE": 0, "PG": 0, "PI": 0, "PS": 0, "PA": 0, "CL": 0, "SM": 0, "CHOL": 0}, "SER-300-PROA": {"PC": 0, "PE": 0, "PG": 0, "PI": 0, "PS": 0, "PA": 0, "CL": 0, "SM": 0, "CHOL": 0}, "PHE-301-PROA": {"PC": 0, "PE": 0, "PG": 0, "PI": 0, "PS": 0, "PA": 0, "CL": 0, "SM": 0, "CHOL": 0}, "VAL-302-PROA": {"PC": 0, "PE": 0, "PG": 0, "PI": 0, "PS": 0, "PA": 0, "CL": 0, "SM": 0, "CHOL": 0}, "GLY-303-PROA": {"PC": 0, "PE": 0, "PG": 0, "PI": 0, "PS": 0, "PA": 0, "CL": 0, "SM": 0, "CHOL": 0}, "ASN-304-PROA": {"PC": 0, "PE": 0, "PG": 0, "PI": 0, "PS": 0, "PA": 0, "CL": 0, "SM": 0, "CHOL": 0}, "TRP-305-PROA": {"PC": 0, "PE": 0, "PG": 0, "PI": 0, "PS": 0, "PA": 0, "CL": 0, "SM": 0, "CHOL": 0}, "GLY-306-PROA": {"PC": 0, "PE": 0, "PG": 0, "PI": 0, "PS": 0, "PA": 0, "CL": 0, "SM": 0, "CHOL": 0}, "PHE-307-PROA": {"PC": 0, "PE": 0, "PG": 0, "PI": 0, "PS": 0, "PA": 0, "CL": 0, "SM": 0, "CHOL": 0}, "SER-308-PROA": {"PC": 0, "PE": 0, "PG": 0, "PI": 0, "PS": 0, "PA": 0, "CL": 0, "SM": 0, "CHOL": 0}, "ILE-309-PROA": {"PC": 0, "PE": 0, "PG": 0, "PI": 0, "PS": 0, "PA": 0, "CL": 0, "SM": 0, "CHOL": 0}, "ILE-310-PROA": {"PC": 0, "PE": 0, "PG": 0, "PI": 0, "PS": 0, "PA": 0, "CL": 0, "SM": 0, "CHOL": 0}, "ILE-311-PROA": {"PC": 0, "PE": 0, "PG": 0, "PI": 0, "PS": 0, "PA": 0, "CL": 0, "SM": 0, "CHOL": 0}, "ILE-312-PROA": {"PC": 0, "PE": 0, "PG": 0, "PI": 0, "PS": 0, "PA": 0, "CL": 0, "SM": 0, "CHOL": 0}, "THR-313-PROA": {"PC": 0, "PE": 0, "PG": 0, "PI": 0, "PS": 0, "PA": 0, "CL": 0, "SM": 0, "CHOL": 0}, "PHE-314-PROA": {"PC": 0, "PE": 0, "PG": 0, "PI": 0, "PS": 0, "PA": 0, "CL": 0, "SM": 0, "CHOL": 0}, "ILE-315-PROA": {"PC": 0, "PE": [-9.645949525796484e-06, -0.001236545409210983, 0.20250275823784264], "PG": 0, "PI": 0, "PS": 0, "PA": 0, "CL": 0, "SM": 0, "CHOL": 0}, "VAL-316-PROA": {"PC": 0, "PE": 0, "PG": 0, "PI": 0, "PS": 0, "PA": 0, "CL": 0, "SM": 0, "CHOL": 0}, "ARG-317-PROA": {"PC": 0, "PE": 0, "PG": 0, "PI": 0, "PS": 0, "PA": 0, "CL": 0, "SM": 0, "CHOL": 0}, "GLY-318-PROA": {"PC": 0, "PE": [-0.17028346075204165, 2.806766213500305, -8.879460435857654], "PG": 0, "PI": 0, "PS": 0, "PA": 0, "CL": 0, "SM": 0, "CHOL": 0}, "ILE-319-PROA": {"PC": 0, "PE": 0, "PG": 0, "PI": 0, "PS": 0, "PA": 0, "CL": 0, "SM": 0, "CHOL": 0}, "MET-320-PROA": {"PC": 0, "PE": 0, "PG": 0, "PI": 0, "PS": 0, "PA": 0, "CL": 0, "SM": 0, "CHOL": 0}, "TYR-321-PROA": {"PC": 0, "PE": 0, "PG": 0, "PI": 0, "PS": 0, "PA": 0, "CL": 0, "SM": 0, "CHOL": 0}, "PRO-322-PROA": {"PC": 0, "PE": [-0.023385683846265888, 0.7248568000758461, -2.9937556218852546], "PG": [1.036477799682031, 4.156275976724942, 16.66666666666702], "PI": 0, "PS": 0, "PA": 0, "CL": 0, "SM": 0, "CHOL": 0}, "LEU-323-PROA": {"PC": 0, "PE": [-7.604791890656354e-06, 0.0002663377004761151, 0.08929428335919506], "PG": [-2.3624972802379228e-06, -0.0010670746323375483, 0.12220594271428087], "PI": 0, "PS": 0, "PA": 0, "CL": 0, "SM": 0, "CHOL": 0}, "THR-324-PROA": {"PC": 0, "PE": [-0.07218279893558209, 1.646176588219085, -5.644335684656644], "PG": 0, "PI": 0, "PS": 0, "PA": 0, "CL": 0, "SM": 0, "CHOL": 0}, "LYS-325-PROA": {"PC": 0, "PE": [2.2299354288837016e-06, -0.0009869130122357496, 0.0592820433943322], "PG": [1.720447013929637e-05, -0.003775334792690947, 0.1383824470861339], "PI": 0, "PS": 0, "PA": 0, "CL": 0, "SM": 0, "CHOL": 0}, "ALA-326-PROA": {"PC": 0, "PE": [7.698609134124849e-08, -0.0001058572887776474, 0.0209402206507387], "PG": [1.6109705209383727e-06, -0.0002877897992949354, 0.01988380869181611], "PI": 0, "PS": 0, "PA": 0, "CL": 0, "SM": 0, "CHOL": 0}, "GLN-327-PROA": {"PC": 0, "PE": [4.089988145296286e-07, -0.0003159944807364533, 0.03708829090828576], "PG": 0, "PI": 0, "PS": 0, "PA": 0, "CL": 0, "SM": 0, "CHOL": 0}, "TYR-328-PROA": {"PC": 0, "PE": [7.968048818212748e-08, -2.1557396542956343e-05, 0.005828472873609251], "PG": 0, "PI": 0, "PS": 0, "PA": 0, "CL": 0, "SM": 0, "CHOL": 0}, "THR-329-PROA": {"PC": 0, "PE": [-4.400844726576627e-08, 3.415874871129184e-05, 0.013380040708271953], "PG": [0.40616058590139315, 1.194151787724166, -11.398531632741026], "PI": 0, "PS": 0, "PA": 0, "CL": 0, "SM": 0, "CHOL": 0}, "SER-330-PROA": {"PC": 0, "PE": [0.0009350378342090867, -0.06255758257697248, 0.7503019873142969], "PG": 0, "PI": 0, "PS": 0, "PA": 0, "CL": 0, "SM": 0, "CHOL": 0}, "MET-331-PROA": {"PC": 0, "PE": [3.111165886740453e-08, -8.775687965009313e-05, 0.014850873054078105], "PG": [1.4985867737430709e-05, -0.00432862665091803, 0.2642142780827505], "PI": 0, "PS": 0, "PA": 0, "CL": 0, "SM": 0, "CHOL": 0}, "ALA-332-PROA": {"PC": 0, "PE": [2.7696591957725883e-09, -1.2329595343290188e-05, 0.008020163885148732], "PG": [5.818216636436653e-06, -0.0035926043330347353, 0.11796620412101017], "PI": 0, "PS": 0, "PA": 0, "CL": 0, "SM": 0, "CHOL": 0}, "LYS-333-PROA": {"PC": 0, "PE": [1.6725889640623226e-07, -0.00020125406751733785, 0.028983795957521954], "PG": [0.10223261412379912, -2.3769833856324376, 11.838292831378395], "PI": 0, "PS": 0, "PA": 0, "CL": 0, "SM": 0, "CHOL": 0}, "MET-334-PROA": {"PC": 0, "PE": [6.609713597350024e-09, -2.379411945972143e-05, 0.015107092190223258], "PG": [-4.7037873968887665e-06, 0.00017723868910500524, 0.055067183502314626], "PI": 0, "PS": 0, "PA": 0, "CL": 0, "SM": 0, "CHOL": 0}, "ARG-335-PROA": {"PC": 0, "PE": [2.6561562563061306e-08, -6.71925133014542e-05, 0.015502709900811085], "PG": [2.0033231505000904e-07, -0.00028165338903821075, 0.02920638328924966], "PI": 0, "PS": 0, "PA": 0, "CL": 0, "SM": 0, "CHOL": 0}, "LYS-352-PROA": {"PC": 0, "PE": [1.0635756860425265e-06, -0.0006235637711801557, 0.06139923396357375], "PG": [1.378859869512973e-06, -0.0007781809389064818, 0.08324288218423222], "PI": 0, "PS": 0, "PA": 0, "CL": 0, "SM": 0, "CHOL": 0}, "GLN-353-PROA": {"PC": 0, "PE": [4.862637853835558e-08, -0.0001183413074184878, 0.02359678120721908], "PG": [3.77857941281971e-08, -5.46520228784355e-05, 0.015503793487297907], "PI": 0, "PS": 0, "PA": 0, "CL": 0, "SM": 0, "CHOL": 0}, "SER-356-PROA": {"PC": 0, "PE": [1.4466170157721823e-08, -6.326475956281538e-05, 0.0140403708916356], "PG": [3.5878786978659106e-09, -1.7051294560492957e-05, 0.011542185653382317], "PI": 0, "PS": 0, "PA": 0, "CL": 0, "SM": 0, "CHOL": 0}, "GLN-357-PROA": {"PC": 0, "PE": 0, "PG": 0, "PI": 0, "PS": 0, "PA": 0, "CL": 0, "SM": 0, "CHOL": 0}, "MET-360-PROA": {"PC": 0, "PE": [3.1006418188979947e-07, -0.0003306206740465697, 0.04048360749395608], "PG": [6.670878371188938e-06, -0.0017767128888607061, 0.0814703495437785], "PI": 0, "PS": 0, "PA": 0, "CL": 0, "SM": 0, "CHOL": 0}, "TYR-363-PROA": {"PC": 0, "PE": [1.6348376939270202e-07, -0.0002030527340414434, 0.029335829508641498], "PG": [2.0319197114988804e-06, -0.0009638201572990688, 0.055511679873523914], "PI": 0, "PS": 0, "PA": 0, "CL": 0, "SM": 0, "CHOL": 0}, "LYS-364-PROA": {"PC": 0, "PE": [8.443892331619435e-08, -0.00015406139284218965, 0.02828015110259157], "PG": [3.1744168939275987e-06, -0.0011142016418076068, 0.06970114258080745], "PI": 0, "PS": 0, "PA": 0, "CL": 0, "SM": 0, "CHOL": 0}, "LYS-367-PROA": {"PC": 0, "PE": [5.428606322902472e-08, -9.105299083567464e-05, 0.017740287353877202], "PG": [3.931056049726308e-07, -0.0003429111370652904, 0.043757611285517445], "PI": 0, "PS": 0, "PA": 0, "CL": 0, "SM": 0, "CHOL": 0}, "VAL-368-PROA": {"PC": 0, "PE": [2.7589699192583286e-07, -0.00023541731786561182, 0.036007116282861705], "PG": [8.22570379190604e-08, -0.0001050726208039133, 0.023799771671344127], "PI": 0, "PS": 0, "PA": 0, "CL": 0, "SM": 0, "CHOL": 0}, "ASN-369-PROA": {"PC": 0, "PE": [2.927231430192251e-06, -0.0011051171379182557, 0.07445995609759759], "PG": [9.310748323729459e-07, -0.000579806735753694, 0.06259602662318872], "PI": 0, "PS": 0, "PA": 0, "CL": 0, "SM": 0, "CHOL": 0}, "PRO-370-PROA": {"PC": 0, "PE": [3.831569406163426e-09, -2.0901931630196452e-05, 0.010621799721826182], "PG": [8.518537057738435e-07, -0.0005108027416710802, 0.05005638508272803], "PI": 0, "PS": 0, "PA": 0, "CL": 0, "SM": 0, "CHOL": 0}, "LEU-371-PROA": {"PC": 0, "PE": [3.976191023689013e-07, -0.00038702173332907485, 0.05205284389188303], "PG": [8.309749944624588e-09, -2.1990976172610364e-05, 0.011196649568171367], "PI": 0, "PS": 0, "PA": 0, "CL": 0, "SM": 0, "CHOL": 0}, "GLY-372-PROA": {"PC": 0, "PE": [-1.256790536908115e-07, -2.1032573070746582e-05, 0.032008338851428376], "PG": [2.2518635814689995e-09, -1.3263275711879925e-05, 0.009438604989794238], "PI": 0, "PS": 0, "PA": 0, "CL": 0, "SM": 0, "CHOL": 0}, "GLY-373-PROA": {"PC": 0, "PE": 0, "PG": 0, "PI": 0, "PS": 0, "PA": 0, "CL": 0, "SM": 0, "CHOL": 0}, "CYS-374-PROA": {"PC": 0, "PE": [6.856200314690504e-08, -0.0001402492732037595, 0.028208377556507173], "PG": [9.029400931034741e-06, -0.0026048165762892635, 0.11242306615642757], "PI": 0, "PS": 0, "PA": 0, "CL": 0, "SM": 0, "CHOL": 0}, "PHE-375-PROA": {"PC": 0, "PE": [9.365926897992718e-05, -0.011344293110604357, 0.3734666656654969], "PG": [4.951373914058903e-07, -0.0003944286162686149, 0.04394376971658642], "PI": 0, "PS": 0, "PA": 0, "CL": 0, "SM": 0, "CHOL": 0}, "PRO-376-PROA": {"PC": 0, "PE": [4.842349330381731e-06, -0.0021083929971982096, 0.1965576636394565], "PG": [2.0049528121834984e-09, -9.862798915519043e-06, 0.010083577207464962], "PI": 0, "PS": 0, "PA": 0, "CL": 0, "SM": 0, "CHOL": 0}, "LEU-377-PROA": {"PC": 0, "PE": [0.4614236025555584, 2.7731558513589056, 16.666666666667027], "PG": 0, "PI": 0, "PS": 0, "PA": 0, "CL": 0, "SM": 0, "CHOL": 0}, "LEU-378-PROA": {"PC": 0, "PE": [1.036477799682031, 4.156275976724942, 16.66666666666702], "PG": [0.00013298343750014143, 0.00015695379332867975, 0.054767355296040966], "PI": 0, "PS": 0, "PA": 0, "CL": 0, "SM": 0, "CHOL": 0}, "ILE-379-PROA": {"PC": 0, "PE": [0.0014304972913485312, -0.08910365061821927, 1.142669852308997], "PG": [1.0796975053864363e-07, -0.00015878076067340753, 0.03679876365522193], "PI": 0, "PS": 0, "PA": 0, "CL": 0, "SM": 0, "CHOL": 0}, "GLN-380-PROA": {"PC": 0, "PE": [4.168769376664039e-06, -0.0009715409960578205, 0.0830372933382388], "PG": 0, "PI": 0, "PS": 0, "PA": 0, "CL": 0, "SM": 0, "CHOL": 0}, "MET-381-PROA": {"PC": 0, "PE": 0, "PG": 0, "PI": 0, "PS": 0, "PA": 0, "CL": 0, "SM": 0, "CHOL": 0}, "PRO-382-PROA": {"PC": 0, "PE": 0, "PG": [-0.008099019071527947, 0.3690172549166604, -2.1531699678927994], "PI": 0, "PS": 0, "PA": 0, "CL": 0, "SM": 0, "CHOL": 0}, "ILE-383-PROA": {"PC": 0, "PE": [9.241579443964578e-07, -0.0005785652869616338, 0.054474087287724], "PG": 0, "PI": 0, "PS": 0, "PA": 0, "CL": 0, "SM": 0, "CHOL": 0}, "PHE-384-PROA": {"PC": 0, "PE": [0.00039047522853686824, -0.03465590800048336, 0.6023540509320233], "PG": [0.001962878311918185, 0.03161002176762023, 0.03349056270686308], "PI": 0, "PS": 0, "PA": 0, "CL": 0, "SM": 0, "CHOL": 0}, "LEU-385-PROA": {"PC": 0, "PE": 0, "PG": 0, "PI": 0, "PS": 0, "PA": 0, "CL": 0, "SM": 0, "CHOL": 0}, "ALA-386-PROA": {"PC": 0, "PE": 0, "PG": 0, "PI": 0, "PS": 0, "PA": 0, "CL": 0, "SM": 0, "CHOL": 0}, "LEU-387-PROA": {"PC": 0, "PE": [5.294763884502555e-08, -0.00010044830105529399, 0.020382887051665435], "PG": 0, "PI": 0, "PS": 0, "PA": 0, "CL": 0, "SM": 0, "CHOL": 0}, "TYR-388-PROA": {"PC": 0, "PE": 0, "PG": 0, "PI": 0, "PS": 0, "PA": 0, "CL": 0, "SM": 0, "CHOL": 0}, "TYR-389-PROA": {"PC": 0, "PE": 0, "PG": 0, "PI": 0, "PS": 0, "PA": 0, "CL": 0, "SM": 0, "CHOL": 0}, "MET-390-PROA": {"PC": 0, "PE": [1.908180485539485e-09, -9.44724472393117e-06, 0.005883875111046801], "PG": 0, "PI": 0, "PS": 0, "PA": 0, "CL": 0, "SM": 0, "CHOL": 0}, "LEU-391-PROA": {"PC": 0, "PE": [3.7262454707879883e-07, -0.0003009172883641002, 0.035878448647155496], "PG": 0, "PI": 0, "PS": 0, "PA": 0, "CL": 0, "SM": 0, "CHOL": 0}, "MET-392-PROA": {"PC": 0, "PE": 0, "PG": 0, "PI": 0, "PS": 0, "PA": 0, "CL": 0, "SM": 0, "CHOL": 0}, "LEU-397-PROA": {"PC": 0, "PE": 0, "PG": 0, "PI": 0, "PS": 0, "PA": 0, "CL": 0, "SM": 0, "CHOL": 0}, "PHE-402-PROA": {"PC": 0, "PE": [3.984614970769175e-08, -6.973067522107754e-05, 0.017246400725957838], "PG": 0, "PI": 0, "PS": 0, "PA": 0, "CL": 0, "SM": 0, "CHOL": 0}, "ALA-403-PROA": {"PC": 0, "PE": [6.509592177164823e-08, -0.00012190662597656715, 0.019190066994791012], "PG": 0, "PI": 0, "PS": 0, "PA": 0, "CL": 0, "SM": 0, "CHOL": 0}, "LEU-404-PROA": {"PC": 0, "PE": [3.2887042711499103e-06, -0.0013538867124215446, 0.08193936552595185], "PG": 0, "PI": 0, "PS": 0, "PA": 0, "CL": 0, "SM": 0, "CHOL": 0}, "TRP-405-PROA": {"PC": 0, "PE": [2.256475499518874e-09, -1.7481166735566306e-05, 0.007814071502052586], "PG": 0, "PI": 0, "PS": 0, "PA": 0, "CL": 0, "SM": 0, "CHOL": 0}, "ILE-406-PROA": {"PC": 0, "PE": [6.674885399651591e-09, -2.732269718114604e-05, 0.013048986521914545], "PG": 0, "PI": 0, "PS": 0, "PA": 0, "CL": 0, "SM": 0, "CHOL": 0}, "LEU-409-PROA": {"PC": 0, "PE": [3.981097051404949e-09, -1.703644475334473e-05, 0.012975345878898464], "PG": [-0.2372412940028759, 4.428564358256849, -15.978709733590074], "PI": 0, "PS": 0, "PA": 0, "CL": 0, "SM": 0, "CHOL": 0}, "ALA-411-PROA": {"PC": 0, "PE": 0, "PG": 0, "PI": 0, "PS": 0, "PA": 0, "CL": 0, "SM": 0, "CHOL": 0}, "GLN-412-PROA": {"PC": 0, "PE": [3.585703493523073e-10, -2.161840299714329e-06, 0.0029016923252714395], "PG": 0, "PI": 0, "PS": 0, "PA": 0, "CL": 0, "SM": 0, "CHOL": 0}, "ASP-413-PROA": {"PC": 0, "PE": [1.3231262746347123e-09, -9.50250179830398e-06, 0.006987838945315791], "PG": [2.0962677865105355e-06, -0.0008202717639290842, 0.07664237724434078], "PI": 0, "PS": 0, "PA": 0, "CL": 0, "SM": 0, "CHOL": 0}, "PRO-414-PROA": {"PC": 0, "PE": [-0.0049309967261498226, 0.19370127749705013, -0.7393845227495826], "PG": [-0.0007574674731449585, 0.037752510303269635, 0.17105030928680556], "PI": 0, "PS": 0, "PA": 0, "CL": 0, "SM": 0, "CHOL": 0}, "TYR-415-PROA": {"PC": 0, "PE": 0, "PG": 0, "PI": 0, "PS": 0, "PA": 0, "CL": 0, "SM": 0, "CHOL": 0}, "TYR-416-PROA": {"PC": 0, "PE": [1.3227869110463524e-08, -3.86570532410168e-05, 0.01927956708024677], "PG": [3.350440084985892e-07, -0.0003682861284806095, 0.043453876906330444], "PI": 0, "PS": 0, "PA": 0, "CL": 0, "SM": 0, "CHOL": 0}, "ILE-417-PROA": {"PC": 0, "PE": [4.723777009203664e-09, -1.3973690738434113e-05, 0.008322413508354559], "PG": [0.001008489228048894, -0.053147016460628096, 0.6122599164470834], "PI": 0, "PS": 0, "PA": 0, "CL": 0, "SM": 0, "CHOL": 0}, "LEU-418-PROA": {"PC": 0, "PE": [1.5432534361909522e-09, -8.15663428288267e-06, 0.007338741296898931], "PG": [1.5297685051327157e-08, -4.0571021539637155e-05, 0.01754505547845189], "PI": 0, "PS": 0, "PA": 0, "CL": 0, "SM": 0, "CHOL": 0}, "PRO-419-PROA": {"PC": 0, "PE": [2.9939450123628632e-09, -1.512653935089348e-05, 0.010647195123855082], "PG": 0, "PI": 0, "PS": 0, "PA": 0, "CL": 0, "SM": 0, "CHOL": 0}, "ILE-420-PROA": {"PC": 0, "PE": [3.733765140508257e-09, -1.7345128777249343e-05, 0.009762161058895548], "PG": [6.986464202612464e-08, -9.744873762397403e-05, 0.020686495160375393], "PI": 0, "PS": 0, "PA": 0, "CL": 0, "SM": 0, "CHOL": 0}, "LEU-421-PROA": {"PC": 0, "PE": 0, "PG": [-0.015146444161935233, 0.37208876776587785, -0.008009717373521128], "PI": 0, "PS": 0, "PA": 0, "CL": 0, "SM": 0, "CHOL": 0}, "MET-422-PROA": {"PC": 0, "PE": [9.50866544848673e-07, -0.000630347635115972, 0.07898315999313392], "PG": 0, "PI": 0, "PS": 0, "PA": 0, "CL": 0, "SM": 0, "CHOL": 0}, "GLY-423-PROA": {"PC": 0, "PE": [1.040178212829431e-08, -3.2622573225392616e-05, 0.014776047193321271], "PG": [4.043061452219183e-06, -0.0018807262463039086, 0.11519800284647738], "PI": 0, "PS": 0, "PA": 0, "CL": 0, "SM": 0, "CHOL": 0}, "VAL-424-PROA": {"PC": 0, "PE": [4.880313628670485e-08, -9.973173630386304e-05, 0.02913791861412075], "PG": [9.453820062937304e-10, -6.1878565333521856e-06, 0.007496200488401459], "PI": 0, "PS": 0, "PA": 0, "CL": 0, "SM": 0, "CHOL": 0}, "THR-425-PROA": {"PC": 0, "PE": [-0.23591204310643557, 0.7647326759623131, 14.800707624048732], "PG": 0, "PI": 0, "PS": 0, "PA": 0, "CL": 0, "SM": 0, "CHOL": 0}, "MET-426-PROA": {"PC": 0, "PE": [-2.1708844036044573e-09, 1.527157406580649e-05, 0.005524641736550797], "PG": [3.137926757284336e-05, -0.0040979741962057885, 0.14204211068979536], "PI": 0, "PS": 0, "PA": 0, "CL": 0, "SM": 0, "CHOL": 0}, "PHE-427-PROA": {"PC": 0, "PE": [3.1434166977917374e-08, -6.738414330674966e-05, 0.01812085279520562], "PG": [1.7623826903703981e-07, -0.00019085590544068863, 0.035604270002026144], "PI": 0, "PS": 0, "PA": 0, "CL": 0, "SM": 0, "CHOL": 0}, "PHE-428-PROA": {"PC": 0, "PE": [2.069621390142478e-07, -0.00026915241142556813, 0.02532989187974148], "PG": [5.059410263445517e-08, -9.942422975891204e-05, 0.02238107918233734], "PI": 0, "PS": 0, "PA": 0, "CL": 0, "SM": 0, "CHOL": 0}, "ILE-429-PROA": {"PC": 0, "PE": [8.375797909184222e-10, -5.396377562879999e-06, 0.007968546223294836], "PG": [0.02464116765996185, -0.7649523064464485, 5.375736541413306], "PI": 0, "PS": 0, "PA": 0, "CL": 0, "SM": 0, "CHOL": 0}, "GLN-430-PROA": {"PC": 0, "PE": [3.225494618088699e-09, -2.142886694753846e-05, 0.007456410108007197], "PG": [5.019986232208642e-05, -0.007455598535016189, 0.20305507393542663], "PI": 0, "PS": 0, "PA": 0, "CL": 0, "SM": 0, "CHOL": 0}, "LYS-431-PROA": {"PC": 0, "PE": [5.353281582167941e-07, -0.0003005716863944504, 0.03393455133803892], "PG": [2.932156861465859e-06, -0.0010429156228401245, 0.059380418394917235], "PI": 0, "PS": 0, "PA": 0, "CL": 0, "SM": 0, "CHOL": 0}, "MET-432-PROA": {"PC": 0, "PE": [9.724693116407575e-07, -0.0003522772895705583, 0.038195995211746395], "PG": [1.506353463906169e-06, -0.0008350784696249805, 0.06277028175025093], "PI": 0, "PS": 0, "PA": 0, "CL": 0, "SM": 0, "CHOL": 0}, "SER-433-PROA": {"PC": 0, "PE": [8.938236038228536e-10, -6.841815139128485e-06, 0.006424815231492851], "PG": [2.6827786495314872e-06, -0.0013726455150634815, 0.12157084705696249], "PI": 0, "PS": 0, "PA": 0, "CL": 0, "SM": 0, "CHOL": 0}, "PRO-434-PROA": {"PC": 0, "PE": [2.4680107093415473e-08, -6.448836401930851e-05, 0.01984401049992799], "PG": [1.1637886038272695e-05, -0.002523798319101212, 0.10162829477075891], "PI": 0, "PS": 0, "PA": 0, "CL": 0, "SM": 0, "CHOL": 0}, "THR-435-PROA": {"PC": 0, "PE": 0, "PG": 0, "PI": 0, "PS": 0, "PA": 0, "CL": 0, "SM": 0, "CHOL": 0}, "THR-436-PROA": {"PC": 0, "PE": 0, "PG": 0, "PI": 0, "PS": 0, "PA": 0, "CL": 0, "SM": 0, "CHOL": 0}, "VAL-437-PROA": {"PC": 0, "PE": [8.592790531812568e-09, -2.6569960249586625e-05, 0.013735337211287186], "PG": [0.0013113554824744488, -0.07551295562358239, 0.8615032836264717], "PI": 0, "PS": 0, "PA": 0, "CL": 0, "SM": 0, "CHOL": 0}, "THR-438-PROA": {"PC": 0, "PE": [1.3476036942720454e-08, -3.1616707201110874e-05, 0.013731804829055198], "PG": [-0.14321044379502598, 2.701656574915913, -9.203420672360668], "PI": 0, "PS": 0, "PA": 0, "CL": 0, "SM": 0, "CHOL": 0}, "ASP-439-PROA": {"PC": 0, "PE": 0, "PG": 0, "PI": 0, "PS": 0, "PA": 0, "CL": 0, "SM": 0, "CHOL": 0}, "PRO-440-PROA": {"PC": 0, "PE": 0, "PG": 0, "PI": 0, "PS": 0, "PA": 0, "CL": 0, "SM": 0, "CHOL": 0}, "MET-441-PROA": {"PC": 0, "PE": [7.768415194795792e-06, -0.0027265147606531258, 0.15215288137547764], "PG": [0.0784978935557879, -1.6896420759280006, 8.826914470802306], "PI": 0, "PS": 0, "PA": 0, "CL": 0, "SM": 0, "CHOL": 0}, "GLN-442-PROA": {"PC": 0, "PE": 0, "PG": 0, "PI": 0, "PS": 0, "PA": 0, "CL": 0, "SM": 0, "CHOL": 0}, "GLN-443-PROA": {"PC": 0, "PE": 0, "PG": 0, "PI": 0, "PS": 0, "PA": 0, "CL": 0, "SM": 0, "CHOL": 0}, "LYS-444-PROA": {"PC": 0, "PE": 0, "PG": 0, "PI": 0, "PS": 0, "PA": 0, "CL": 0, "SM": 0, "CHOL": 0}, "ILE-445-PROA": {"PC": 0, "PE": 0, "PG": 0, "PI": 0, "PS": 0, "PA": 0, "CL": 0, "SM": 0, "CHOL": 0}, "MET-446-PROA": {"PC": 0, "PE": 0, "PG": 0, "PI": 0, "PS": 0, "PA": 0, "CL": 0, "SM": 0, "CHOL": 0}, "THR-447-PROA": {"PC": 0, "PE": 0, "PG": [0.2224836027242896, -1.2028166143073644, -0.3080671898603812], "PI": 0, "PS": 0, "PA": 0, "CL": 0, "SM": 0, "CHOL": 0}, "PHE-448-PROA": {"PC": 0, "PE": 0, "PG": 0, "PI": 0, "PS": 0, "PA": 0, "CL": 0, "SM": 0, "CHOL": 0}, "MET-449-PROA": {"PC": 0, "PE": 0, "PG": 0, "PI": 0, "PS": 0, "PA": 0, "CL": 0, "SM": 0, "CHOL": 0}, "PRO-450-PROA": {"PC": 0, "PE": [5.582852090722935e-07, -0.00047186217506825766, 0.05893068385093417], "PG": [1.0842963681757764e-06, -0.0006599561359782584, 0.052960089267069174], "PI": 0, "PS": 0, "PA": 0, "CL": 0, "SM": 0, "CHOL": 0}, "VAL-451-PROA": {"PC": 0, "PE": [5.4606434194984535e-08, -8.797903458037469e-05, 0.0196633236785852], "PG": [2.3952100460258543e-08, -4.083543689047842e-05, 0.012598568874134963], "PI": 0, "PS": 0, "PA": 0, "CL": 0, "SM": 0, "CHOL": 0}, "ILE-452-PROA": {"PC": 0, "PE": [9.27480210837595e-08, -0.00013094802089802401, 0.033189812786806015], "PG": [1.1760663151407884e-08, -1.987689224194109e-05, 0.007664437099165584], "PI": 0, "PS": 0, "PA": 0, "CL": 0, "SM": 0, "CHOL": 0}, "PHE-453-PROA": {"PC": 0, "PE": [1.1040911802318162e-08, -3.586674643612843e-05, 0.01512739569858319], "PG": [1.0099970840582883e-07, -9.934426062928327e-05, 0.020098105832451484], "PI": 0, "PS": 0, "PA": 0, "CL": 0, "SM": 0, "CHOL": 0}, "THR-454-PROA": {"PC": 0, "PE": [2.0399048452759947e-08, -5.3594528025001e-05, 0.019801363720797955], "PG": [4.110839564999427e-06, -0.00134035658437142, 0.0762591870766209], "PI": 0, "PS": 0, "PA": 0, "CL": 0, "SM": 0, "CHOL": 0}, "VAL-455-PROA": {"PC": 0, "PE": [-1.8170893251610326e-08, -8.792155889363455e-05, 0.028035621698415187], "PG": [0.0006280005283132045, -0.043553148897088466, 0.5255598998177942], "PI": 0, "PS": 0, "PA": 0, "CL": 0, "SM": 0, "CHOL": 0}, "PHE-456-PROA": {"PC": 0, "PE": [9.282857752831855e-06, -0.0030438178692325096, 0.09949901830576162], "PG": [0.0008221863715619568, -0.03626188761693571, 0.411623670637633], "PI": 0, "PS": 0, "PA": 0, "CL": 0, "SM": 0, "CHOL": 0}, "PHE-457-PROA": {"PC": 0, "PE": 0, "PG": 0, "PI": 0, "PS": 0, "PA": 0, "CL": 0, "SM": 0, "CHOL": 0}, "LEU-458-PROA": {"PC": 0, "PE": 0, "PG": 0, "PI": 0, "PS": 0, "PA": 0, "CL": 0, "SM": 0, "CHOL": 0}, "TRP-459-PROA": {"PC": 0, "PE": 0, "PG": 0, "PI": 0, "PS": 0, "PA": 0, "CL": 0, "SM": 0, "CHOL": 0}, "PHE-460-PROA": {"PC": 0, "PE": [-0.9556781369901699, 1.8393623919967224, 36.30480983075757], "PG": [0.0002703472353648282, -0.029756986998752098, 0.7469273035876254], "PI": 0, "PS": 0, "PA": 0, "CL": 0, "SM": 0, "CHOL": 0}, "PRO-461-PROA": {"PC": 0, "PE": [8.274816908792908e-05, -0.011497947680419073, 0.2682529618773299], "PG": [1.1625983342407592e-05, -0.003155852865713434, 0.09502914194652026], "PI": 0, "PS": 0, "PA": 0, "CL": 0, "SM": 0, "CHOL": 0}, "SER-462-PROA": {"PC": 0, "PE": [0.016338525840431013, -0.658574563133376, 4.175142964740968], "PG": [-20.632324712063117, 206.07067084259526, -492.99727849060656], "PI": 0, "PS": 0, "PA": 0, "CL": 0, "SM": 0, "CHOL": 0}, "GLY-463-PROA": {"PC": 0, "PE": [1.6628870125822391e-06, -0.0006159851074501862, 0.04156757615678822], "PG": [0.0002238854214463851, -0.09060945095504593, 1.4479776078196152], "PI": 0, "PS": 0, "PA": 0, "CL": 0, "SM": 0, "CHOL": 0}, "LEU-464-PROA": {"PC": 0, "PE": [1.8913715613933465e-08, -3.7363026705451965e-05, 0.011611855544877984], "PG": [-0.00011366681268560175, 0.013340447241713946, -0.03823333335304807], "PI": 0, "PS": 0, "PA": 0, "CL": 0, "SM": 0, "CHOL": 0}, "VAL-465-PROA": {"PC": 0, "PE": [1.4219243924261093e-08, -3.80032703477892e-05, 0.01425028194495494], "PG": [6.81381846513746e-08, -0.00010647259255608358, 0.020858204941216905], "PI": 0, "PS": 0, "PA": 0, "CL": 0, "SM": 0, "CHOL": 0}, "LEU-466-PROA": {"PC": 0, "PE": [7.664619883674207e-08, -0.00012302026158520117, 0.02616938043587215], "PG": [1.4777310361142965e-05, -0.0033579223523705296, 0.15818172447928544], "PI": 0, "PS": 0, "PA": 0, "CL": 0, "SM": 0, "CHOL": 0}, "TYR-467-PROA": {"PC": 0, "PE": [1.234228986106247e-06, -0.00073810765820909, 0.06656318828816382], "PG": [2.408677890888065e-06, -0.0012451114384016055, 0.09258691958427223], "PI": 0, "PS": 0, "PA": 0, "CL": 0, "SM": 0, "CHOL": 0}, "TYR-468-PROA": {"PC": 0, "PE": [2.305556174359646e-06, -0.0008753088480798587, 0.06268873703469303], "PG": [1.1505921054688672e-05, -0.002434850884292615, 0.09724984201530437], "PI": 0, "PS": 0, "PA": 0, "CL": 0, "SM": 0, "CHOL": 0}, "ILE-469-PROA": {"PC": 0, "PE": [4.739701887657777e-08, -0.00010580358977288524, 0.022983624465257046], "PG": [4.1252435997327884e-07, -0.00035415722067430643, 0.03641739691576063], "PI": 0, "PS": 0, "PA": 0, "CL": 0, "SM": 0, "CHOL": 0}, "VAL-470-PROA": {"PC": 0, "PE": [9.41847931802564e-08, -0.00015393531127376128, 0.025996931838585483], "PG": [5.1245019191921195e-06, -0.0020238979810481604, 0.12007952486120942], "PI": 0, "PS": 0, "PA": 0, "CL": 0, "SM": 0, "CHOL": 0}, "SER-471-PROA": {"PC": 0, "PE": [0.0004146980025810163, -0.025194628194970665, 0.3501627998953887], "PG": [0.04014514974661468, -0.6589377027029892, 2.8102902390117968], "PI": 0, "PS": 0, "PA": 0, "CL": 0, "SM": 0, "CHOL": 0}, "ASN-472-PROA": {"PC": 0, "PE": [2.0186556891223915e-06, -0.000788326381016007, 0.06683763293349128], "PG": [9.363260105346323e-10, -6.328443116831781e-06, 0.008917502304681378], "PI": 0, "PS": 0, "PA": 0, "CL": 0, "SM": 0, "CHOL": 0}, "LEU-473-PROA": {"PC": 0, "PE": [2.516846556491195e-07, -0.0002479149162700115, 0.030569046201814956], "PG": [2.3706779959368916e-06, -0.0011620140770634323, 0.07788494122130099], "PI": 0, "PS": 0, "PA": 0, "CL": 0, "SM": 0, "CHOL": 0}, "VAL-474-PROA": {"PC": 0, "PE": [2.7731988559278612e-06, -0.0011029562490374283, 0.06523572023647163], "PG": [-0.0003137316150972355, 0.02223770721214805, 0.19965832392645583], "PI": 0, "PS": 0, "PA": 0, "CL": 0, "SM": 0, "CHOL": 0}, "THR-475-PROA": {"PC": 0, "PE": [9.618241741191544e-08, -8.846185017174361e-05, 0.01468500533668927], "PG": [4.665703518377984e-09, -1.0429924458614164e-05, 0.004668949373622382], "PI": 0, "PS": 0, "PA": 0, "CL": 0, "SM": 0, "CHOL": 0}, "ILE-476-PROA": {"PC": 0, "PE": [1.9027746437084568e-07, -0.00022662892423318167, 0.037248461783625945], "PG": [5.637308522725323e-10, -4.9216120235575346e-06, 0.006872602041686734], "PI": 0, "PS": 0, "PA": 0, "CL": 0, "SM": 0, "CHOL": 0}, "ILE-477-PROA": {"PC": 0, "PE": [2.0223328833237804e-09, -1.0517073797938608e-05, 0.008949487445475706], "PG": [0.001592067478947178, -0.10574682243077135, 1.3750136156965351], "PI": 0, "PS": 0, "PA": 0, "CL": 0, "SM": 0, "CHOL": 0}, "GLN-478-PROA": {"PC": 0, "PE": [1.5651488126187117e-06, -0.0007068375091835611, 0.06472172884051491], "PG": 0, "PI": 0, "PS": 0, "PA": 0, "CL": 0, "SM": 0, "CHOL": 0}, "GLN-479-PROA": {"PC": 0, "PE": [4.0760288462039427e-11, -3.7475012766996444e-07, 0.0014719601447901324], "PG": [4.1410550550338135e-10, -2.3555982358714093e-06, 0.002800545792571884], "PI": 0, "PS": 0, "PA": 0, "CL": 0, "SM": 0, "CHOL": 0}, "GLN-480-PROA": {"PC": 0, "PE": [4.3107542746195393e-07, -0.00038752395582918736, 0.04629391588993039], "PG": [3.067834573195317e-08, -6.603202055624087e-05, 0.016880625181940712], "PI": 0, "PS": 0, "PA": 0, "CL": 0, "SM": 0, "CHOL": 0}, "LEU-481-PROA": {"PC": 0, "PE": [1.718125379267869e-08, -3.793014388647686e-05, 0.013831353745147242], "PG": [5.8732369886702863e-05, -0.006913371506616543, 0.160813425663837], "PI": 0, "PS": 0, "PA": 0, "CL": 0, "SM": 0, "CHOL": 0}, "ILE-482-PROA": {"PC": 0, "PE": [2.2033482410130155e-10, -1.417514948173152e-06, 0.0019958629511542363], "PG": [0.004582843921213339, -0.2969412962318453, 2.8747572370067123], "PI": 0, "PS": 0, "PA": 0, "CL": 0, "SM": 0, "CHOL": 0}, "TYR-483-PROA": {"PC": 0, "PE": [-5.428733401194173e-08, -4.071844666861926e-05, 0.04161577040645729], "PG": [5.2699644104404454e-05, -0.010943286902639713, 0.29753152786147335], "PI": 0, "PS": 0, "PA": 0, "CL": 0, "SM": 0, "CHOL": 0}}